erk_kits/__init__.py
erk_kits/data/__init__.py
erk_kits/data/kits/__init__.py
erk_kits/data/kits/registry.yaml
erk_kits/data/kits/command/kit.yaml
erk_kits/data/kits/command/scripts/command/__init__.py
erk_kits/data/kits/command/scripts/command/execute.py
erk_kits/data/kits/command/scripts/command/formatting.py
erk_kits/data/kits/command/scripts/command/message_parsing.py
erk_kits/data/kits/command/scripts/command/models.py
erk_kits/data/kits/command/scripts/command/ops.py
erk_kits/data/kits/command/scripts/command/resolution.py
erk_kits/data/kits/devrun/__init__.py
erk_kits/data/kits/devrun/kit.yaml
erk_kits/data/kits/devrun/agents/__init__.py
erk_kits/data/kits/devrun/agents/devrun/__init__.py
erk_kits/data/kits/devrun/docs/__init__.py
erk_kits/data/kits/devrun/docs/devrun/__init__.py
erk_kits/data/kits/devrun/docs/devrun/tools/__init__.py
erk_kits/data/kits/devrun/scripts/__init__.py
erk_kits/data/kits/devrun/scripts/devrun/__init__.py
erk_kits/data/kits/devrun/scripts/devrun/devrun_reminder_hook.py
erk_kits/data/kits/dignified-python/__init__.py
erk_kits/data/kits/dignified-python/kit.yaml
erk_kits/data/kits/dignified-python/scripts/dignified-python/version_aware_reminder_hook.py
erk_kits/data/kits/dignified-python/skills/dignified-python-310/__init__.py
erk_kits/data/kits/dignified-python/skills/dignified-python-311/__init__.py
erk_kits/data/kits/dignified-python/skills/dignified-python-312/__init__.py
erk_kits/data/kits/dignified-python/skills/dignified-python-313/__init__.py
erk_kits/data/kits/erk/README.md
erk_kits/data/kits/erk/__init__.py
erk_kits/data/kits/erk/kit.yaml
erk_kits/data/kits/erk/plan_utils.py
erk_kits/data/kits/erk/session_plan_extractor.py
erk_kits/data/kits/erk/commands/__init__.py
erk_kits/data/kits/erk/commands/erk/__init__.py
erk_kits/data/kits/erk/scripts/erk/add_issue_label.py
erk_kits/data/kits/erk/scripts/erk/add_reaction_to_comment.py
erk_kits/data/kits/erk/scripts/erk/add_remote_execution_note.py
erk_kits-0.2.8.dist-info/METADATA
erk_kits-0.2.8.dist-info/WHEEL
erk_kits-0.2.8.dist-info/RECORD
