Metadata-Version: 2.4
Name: erk-kits
Version: 0.2.8
Summary: Bundled kit data for erk
Requires-Python: >=3.11
